vnstockdata/__init__.py
vnstockdata/connect.py
vnstockdata/ticker.py
vnstockdata/client/__init__.py
vnstockdata/client/login.cpython-310-darwin.so
vnstockdata/config/__init__.py
vnstockdata/config/config.cpython-310-darwin.so
vnstockdata/config/ensure_logged_in.cpython-310-darwin.so
vnstockdata/stock/__init__.py
vnstockdata/stock/price.cpython-310-darwin.so
library_test-0.5.17.dist-info/METADATA
library_test-0.5.17.dist-info/WHEEL
library_test-0.5.17.dist-info/top_level.txt
library_test-0.5.17.dist-info/RECORD
