Metadata-Version: 2.1
Name: library-test
Version: 0.5.17
Summary: Mô tả thư viện của bạn
Home-page: https://vnstockdata.com
Author: vnstockdata.com
Author-email: support@vnstockdata.com
Classifier: Programming Language :: Python :: 3
Classifier: License :: OSI Approved :: MIT License
Classifier: Operating System :: OS Independent
Requires-Python: >=3.9
Requires-Dist: pandas==2.1.2
Requires-Dist: requests
